ml_cloud_tools/__init__.py
ml_cloud_tools/s3.py
ml_cloud_tools-0.0.1.dist-info/LICENSE
ml_cloud_tools-0.0.1.dist-info/METADATA
ml_cloud_tools-0.0.1.dist-info/WHEEL
ml_cloud_tools-0.0.1.dist-info/top_level.txt
ml_cloud_tools-0.0.1.dist-info/RECORD
