Metadata-Version: 2.1
Name: ml-cloud-tools
Version: 0.0.1
Summary: ML Tools for the Cloud
Home-page: https://github.com/telekom/ml-cloud-tools
Author: Philip May
Author-email: philip.may@t-systems.com
Maintainer: Philip May
Project-URL: Bug Tracker, https://github.com/telekom/ml-cloud-tools/issues
Project-URL: Code Doc, https://telekom.github.io/ml-cloud-tools/
Project-URL: Source Code, https://github.com/telekom/ml-cloud-tools
Project-URL: Contributing, https://github.com/telekom/ml-cloud-tools/blob/main/CONTRIBUTING.md
Project-URL: Code of Conduct, https://github.com/telekom/ml-cloud-tools/blob/main/CODE_OF_CONDUCT.md
Keywords: cloud aws boto3 s3
Classifier: Development Status :: 3 - Alpha
Classifier: Intended Audience :: Science/Research
Classifier: Intended Audience :: Education
Classifier: Intended Audience :: Developers
Classifier: License :: OSI Approved :: MIT License
Classifier: Programming Language :: Python :: 3
Classifier: Programming Language :: Python :: 3.7
Classifier: Programming Language :: Python :: 3.8
Classifier: Programming Language :: Python :: 3.9
Classifier: Programming Language :: Python :: 3.10
Classifier: Programming Language :: Python :: 3.11
Classifier: Programming Language :: Python :: 3 :: Only
Classifier: Topic :: Scientific/Engineering
Classifier: Topic :: Scientific/Engineering :: Mathematics
Classifier: Topic :: Scientific/Engineering :: Artificial Intelligence
Classifier: Topic :: Software Development
Classifier: Topic :: Software Development :: Libraries
Classifier: Topic :: Software Development :: Libraries :: Python Modules
Classifier: Operating System :: OS Independent
Requires-Python: >=3.7
License-File: LICENSE
Requires-Dist: boto3
Provides-Extra: all
Requires-Dist: isort ; extra == 'all'
Requires-Dist: pylint ; extra == 'all'
Requires-Dist: sphinx-copybutton ; extra == 'all'
Requires-Dist: myst-parser ; extra == 'all'
Requires-Dist: sphinx-rtd-theme ; extra == 'all'
Requires-Dist: flake8 ; extra == 'all'
Requires-Dist: pydocstyle ; extra == 'all'
Requires-Dist: mdformat ; extra == 'all'
Requires-Dist: moto ; extra == 'all'
Requires-Dist: packaging ; extra == 'all'
Requires-Dist: pylintfileheader ; extra == 'all'
Requires-Dist: sphinx ; extra == 'all'
Requires-Dist: mypy ; extra == 'all'
Requires-Dist: black ; extra == 'all'
Requires-Dist: pytest ; extra == 'all'
Provides-Extra: checking
Requires-Dist: black ; extra == 'checking'
Requires-Dist: flake8 ; extra == 'checking'
Requires-Dist: isort ; extra == 'checking'
Requires-Dist: mdformat ; extra == 'checking'
Requires-Dist: pydocstyle ; extra == 'checking'
Requires-Dist: mypy ; extra == 'checking'
Requires-Dist: pylint ; extra == 'checking'
Requires-Dist: pylintfileheader ; extra == 'checking'
Provides-Extra: doc
Requires-Dist: sphinx ; extra == 'doc'
Requires-Dist: sphinx-rtd-theme ; extra == 'doc'
Requires-Dist: myst-parser ; extra == 'doc'
Requires-Dist: sphinx-copybutton ; extra == 'doc'
Provides-Extra: testing
Requires-Dist: pytest ; extra == 'testing'
Requires-Dist: moto ; extra == 'testing'
Requires-Dist: packaging ; extra == 'testing'
